{"response": {"status": {"version": "4.2", "code": 0, "message": "Success"}, "track": {"status": "complete", "song_id": "SOTXITQ131343990DB", "artist": "Al Green", "foreign_ids": ["spotify-AD:track:13FkFPnKX1eC2V3nwSy5YB", "spotify-AR:track:13FkFPnKX1eC2V3nwSy5YB", "spotify-AT:track:13FkFPnKX1eC2V3nwSy5YB", "spotify-AU:track:13FkFPnKX1eC2V3nwSy5YB", "spotify-BE:track:13FkFPnKX1eC2V3nwSy5YB", "spotify-BG:track:13FkFPnKX1eC2V3nwSy5YB", "spotify-BO:track:13FkFPnKX1eC2V3nwSy5YB", "spotify-CA:track:13FkFPnKX1eC2V3nwSy5YB", "spotify-CH:track:13FkFPnKX1eC2V3nwSy5YB", "spotify-CL:track:13FkFPnKX1eC2V3nwSy5YB", "spotify-CO:track:13FkFPnKX1eC2V3nwSy5YB", "spotify-CR:track:13FkFPnKX1eC2V3nwSy5YB", "spotify-CY:track:13FkFPnKX1eC2V3nwSy5YB", "spotify-CZ:track:13FkFPnKX1eC2V3nwSy5YB", "spotify-DE:track:13FkFPnKX1eC2V3nwSy5YB", "spotify-DK:track:13FkFPnKX1eC2V3nwSy5YB", "spotify-DO:track:13FkFPnKX1eC2V3nwSy5YB", "spotify-EC:track:13FkFPnKX1eC2V3nwSy5YB", "spotify-EE:track:13FkFPnKX1eC2V3nwSy5YB", "spotify-ES:track:13FkFPnKX1eC2V3nwSy5YB", "spotify-FI:track:13FkFPnKX1eC2V3nwSy5YB", "spotify-FR:track:13FkFPnKX1eC2V3nwSy5YB", "spotify-GB:track:13FkFPnKX1eC2V3nwSy5YB", "spotify-GR:track:13FkFPnKX1eC2V3nwSy5YB", "spotify-GT:track:13FkFPnKX1eC2V3nwSy5YB", "spotify-HK:track:13FkFPnKX1eC2V3nwSy5YB", "spotify-HN:track:13FkFPnKX1eC2V3nwSy5YB", "spotify-HR:track:13FkFPnKX1eC2V3nwSy5YB", "spotify-HU:track:13FkFPnKX1eC2V3nwSy5YB", "spotify-IE:track:13FkFPnKX1eC2V3nwSy5YB", "spotify-IS:track:13FkFPnKX1eC2V3nwSy5YB", "spotify-IT:track:13FkFPnKX1eC2V3nwSy5YB", "spotify-LI:track:13FkFPnKX1eC2V3nwSy5YB", "spotify-LT:track:13FkFPnKX1eC2V3nwSy5YB", "spotify-LU:track:13FkFPnKX1eC2V3nwSy5YB", "spotify-LV:track:13FkFPnKX1eC2V3nwSy5YB", "spotify-MC:track:13FkFPnKX1eC2V3nwSy5YB", "spotify-MT:track:13FkFPnKX1eC2V3nwSy5YB", "spotify-MX:track:13FkFPnKX1eC2V3nwSy5YB", "spotify-MY:track:13FkFPnKX1eC2V3nwSy5YB", "spotify-NI:track:13FkFPnKX1eC2V3nwSy5YB", "spotify-NL:track:13FkFPnKX1eC2V3nwSy5YB", "spotify-NO:track:13FkFPnKX1eC2V3nwSy5YB", "spotify-NZ:track:13FkFPnKX1eC2V3nwSy5YB", "spotify-PA:track:13FkFPnKX1eC2V3nwSy5YB", "spotify-PE:track:13FkFPnKX1eC2V3nwSy5YB", "spotify-PH:track:13FkFPnKX1eC2V3nwSy5YB", "spotify-PL:track:13FkFPnKX1eC2V3nwSy5YB", "spotify-PT:track:13FkFPnKX1eC2V3nwSy5YB", "spotify-PY:track:13FkFPnKX1eC2V3nwSy5YB", "spotify-RO:track:13FkFPnKX1eC2V3nwSy5YB", "spotify-SE:track:13FkFPnKX1eC2V3nwSy5YB", "spotify-SG:track:13FkFPnKX1eC2V3nwSy5YB", "spotify-SI:track:13FkFPnKX1eC2V3nwSy5YB", "spotify-SK:track:13FkFPnKX1eC2V3nwSy5YB", "spotify-SV:track:13FkFPnKX1eC2V3nwSy5YB", "spotify-TR:track:13FkFPnKX1eC2V3nwSy5YB", "spotify-TW:track:13FkFPnKX1eC2V3nwSy5YB", "spotify-US:track:13FkFPnKX1eC2V3nwSy5YB", "spotify-UY:track:13FkFPnKX1eC2V3nwSy5YB", "spotify:track:13FkFPnKX1eC2V3nwSy5YB"], "title": "Love And Happiness", "foreign_release_ids": ["spotify-AD:album:0fgloBlv8EpPqyL4j1W4AO", "spotify-AR:album:0fgloBlv8EpPqyL4j1W4AO", "spotify-AT:album:0fgloBlv8EpPqyL4j1W4AO", "spotify-AU:album:0fgloBlv8EpPqyL4j1W4AO", "spotify-BE:album:0fgloBlv8EpPqyL4j1W4AO", "spotify-BG:album:0fgloBlv8EpPqyL4j1W4AO", "spotify-BO:album:0fgloBlv8EpPqyL4j1W4AO", "spotify-CA:album:0fgloBlv8EpPqyL4j1W4AO", "spotify-CH:album:0fgloBlv8EpPqyL4j1W4AO", "spotify-CL:album:0fgloBlv8EpPqyL4j1W4AO", "spotify-CO:album:0fgloBlv8EpPqyL4j1W4AO", "spotify-CR:album:0fgloBlv8EpPqyL4j1W4AO", "spotify-CY:album:0fgloBlv8EpPqyL4j1W4AO", "spotify-CZ:album:0fgloBlv8EpPqyL4j1W4AO", "spotify-DE:album:0fgloBlv8EpPqyL4j1W4AO", "spotify-DK:album:0fgloBlv8EpPqyL4j1W4AO", "spotify-DO:album:0fgloBlv8EpPqyL4j1W4AO", "spotify-EC:album:0fgloBlv8EpPqyL4j1W4AO", "spotify-EE:album:0fgloBlv8EpPqyL4j1W4AO", "spotify-ES:album:0fgloBlv8EpPqyL4j1W4AO", "spotify-FI:album:0fgloBlv8EpPqyL4j1W4AO", "spotify-FR:album:0fgloBlv8EpPqyL4j1W4AO", "spotify-GB:album:0fgloBlv8EpPqyL4j1W4AO", "spotify-GR:album:0fgloBlv8EpPqyL4j1W4AO", "spotify-GT:album:0fgloBlv8EpPqyL4j1W4AO", "spotify-HK:album:0fgloBlv8EpPqyL4j1W4AO", "spotify-HN:album:0fgloBlv8EpPqyL4j1W4AO", "spotify-HR:album:0fgloBlv8EpPqyL4j1W4AO", "spotify-HU:album:0fgloBlv8EpPqyL4j1W4AO", "spotify-IE:album:0fgloBlv8EpPqyL4j1W4AO", "spotify-IS:album:0fgloBlv8EpPqyL4j1W4AO", "spotify-IT:album:0fgloBlv8EpPqyL4j1W4AO", "spotify-LI:album:0fgloBlv8EpPqyL4j1W4AO", "spotify-LT:album:0fgloBlv8EpPqyL4j1W4AO", "spotify-LU:album:0fgloBlv8EpPqyL4j1W4AO", "spotify-LV:album:0fgloBlv8EpPqyL4j1W4AO", "spotify-MC:album:0fgloBlv8EpPqyL4j1W4AO", "spotify-MT:album:0fgloBlv8EpPqyL4j1W4AO", "spotify-MX:album:0fgloBlv8EpPqyL4j1W4AO", "spotify-MY:album:0fgloBlv8EpPqyL4j1W4AO", "spotify-NI:album:0fgloBlv8EpPqyL4j1W4AO", "spotify-NL:album:0fgloBlv8EpPqyL4j1W4AO", "spotify-NO:album:0fgloBlv8EpPqyL4j1W4AO", "spotify-NZ:album:0fgloBlv8EpPqyL4j1W4AO", "spotify-PA:album:0fgloBlv8EpPqyL4j1W4AO", "spotify-PE:album:0fgloBlv8EpPqyL4j1W4AO", "spotify-PH:album:0fgloBlv8EpPqyL4j1W4AO", "spotify-PL:album:0fgloBlv8EpPqyL4j1W4AO", "spotify-PT:album:0fgloBlv8EpPqyL4j1W4AO", "spotify-PY:album:0fgloBlv8EpPqyL4j1W4AO", "spotify-RO:album:0fgloBlv8EpPqyL4j1W4AO", "spotify-SE:album:0fgloBlv8EpPqyL4j1W4AO", "spotify-SG:album:0fgloBlv8EpPqyL4j1W4AO", "spotify-SI:album:0fgloBlv8EpPqyL4j1W4AO", "spotify-SK:album:0fgloBlv8EpPqyL4j1W4AO", "spotify-SV:album:0fgloBlv8EpPqyL4j1W4AO", "spotify-TR:album:0fgloBlv8EpPqyL4j1W4AO", "spotify-TW:album:0fgloBlv8EpPqyL4j1W4AO", "spotify-US:album:0fgloBlv8EpPqyL4j1W4AO", "spotify-UY:album:0fgloBlv8EpPqyL4j1W4AO", "spotify:album:0fgloBlv8EpPqyL4j1W4AO"], "foreign_release_id": "spotify-AD:album:0fgloBlv8EpPqyL4j1W4AO", "catalog": "spotify-AD", "release": "Greatest Hits", "audio_md5": "e609de57eb7fd5b0842fab46c456927e", "foreign_id": "spotify-AD:track:13FkFPnKX1eC2V3nwSy5YB", "id": "TRCTOVV144D0BBE2A0", "audio_summary": {"time_signature": 4, "tempo": 99.818, "energy": 0.43513223960311304, "liveness": 0.08023648704656001, "analysis_url": "http://echonest-analysis.s3.amazonaws.com/TR/ltE2fQRBOmBoEslINtsoi-f8v-aZM-DRzEsbhxfkfpRF0qkvz0mggZFzuuaN-KYn6rofFYq7ryP4bT18g%3D/3/full.json?AWSAccessKeyId=AKIAJRDFEY23UEVW42BQ&Expires=1425158225&Signature=/MQTfqFXaaq3AftrW4hdov8LtCY%3D", "speechiness": 0.1608043624467958, "mode": 0, "acousticness": 0.30569999922278596, "danceability": 0.8220122532471702, "key": 8, "duration": 303.53288, "loudness": -10.979, "valence": 0.742303636069935, "instrumentalness": 0.0061165239243130606}}}}