{"response": {"status": {"version": "4.2", "code": 0, "message": "Success"}, "track": {"status": "complete", "song_id": "SOBFUNU142F04B6AAB", "artist": "Stevie Wonder", "foreign_ids": ["spotify-CA:track:1bpoXeCrptBmDnLrZSR42i", "spotify-MX:track:1bpoXeCrptBmDnLrZSR42i", "spotify-US:track:1bpoXeCrptBmDnLrZSR42i", "spotify:track:1bpoXeCrptBmDnLrZSR42i"], "title": "Superstition", "foreign_release_ids": ["spotify-CA:album:7LNgQwnKshnUmzyD71PPDH", "spotify-MX:album:7LNgQwnKshnUmzyD71PPDH", "spotify-US:album:7LNgQwnKshnUmzyD71PPDH", "spotify:album:7LNgQwnKshnUmzyD71PPDH"], "foreign_release_id": "spotify-CA:album:7LNgQwnKshnUmzyD71PPDH", "catalog": "spotify-CA", "release": "The Complete Motown Singles Vol. 12B: 1972", "audio_md5": "5737f9d583a5095e328cf46ae03671ef", "foreign_id": "spotify-CA:track:1bpoXeCrptBmDnLrZSR42i", "id": "TRCODOA144D0D3A79D", "audio_summary": {"time_signature": 4, "tempo": 100.494, "energy": 0.7798589834424468, "liveness": 0.03567842626529456, "analysis_url": "http://echonest-analysis.s3.amazonaws.com/TR/hHK0Fgp6Rvi6uR7y95LMWewHBwMug0vLvVVciuwi9mEPokXewSAisudnQKPkAbGrzwo_TfrsQEknL2GHU%3D/3/full.json?AWSAccessKeyId=AKIAJRDFEY23UEVW42BQ&Expires=1425158332&Signature=6YV%2B1E4VQcDgY8SIfPkvRDbbtu4%3D", "speechiness": 0.07346759476412273, "mode": 1, "acousticness": 0.06394057227698724, "danceability": 0.6399772779271856, "key": 8, "duration": 247.54621, "loudness": -8.373, "valence": 0.9121119654038039, "instrumentalness": 0.001467457402648045}}}}